README.md
setup.py
pycraftco/__init__.py
pycraftco/craft_api_schema.py
pycraftco.egg-info/PKG-INFO
pycraftco.egg-info/SOURCES.txt
pycraftco.egg-info/dependency_links.txt
pycraftco.egg-info/requires.txt
pycraftco.egg-info/top_level.txt