Metadata-Version: 2.1
Name: pycraftco
Version: 0.0.1
Summary: pycraftco is a Python library that serves as a convenient wrapper for Craft API (https://api.craft.co/docs/v1)
Home-page: https://github.com/craft-machine/pycraftco
Author: Craft Machine Inc
License: UNKNOWN
Keywords: SDK,API
Platform: UNKNOWN
Classifier: License :: OSI Approved :: MIT License
Classifier: Operating System :: OS Independent
Classifier: Programming Language :: Python
Classifier: Programming Language :: Python :: 3
Classifier: Topic :: Utilities
